laicheil/__init__.py
laicheil/force2019/__init__.py
laicheil/force2019/_version.py
laicheil/force2019/argparse_tree.py
laicheil/force2019/blank.py
laicheil/force2019/cli.py
laicheil/force2019/some.py
laicheil.force2019-0.post0.dev10.dist-info/LICENSE
laicheil.force2019-0.post0.dev10.dist-info/METADATA
laicheil.force2019-0.post0.dev10.dist-info/WHEEL
laicheil.force2019-0.post0.dev10.dist-info/entry_points.txt
laicheil.force2019-0.post0.dev10.dist-info/top_level.txt
laicheil.force2019-0.post0.dev10.dist-info/RECORD
