Metadata-Version: 2.1
Name: laicheil.force2019
Version: 0.post0.dev10
Summary: ...
Home-page: https://example.com/
License: MIT
Platform: UNKNOWN
Classifier: Development Status :: 3 - Alpha
Classifier: Programming Language :: Python :: 3
Requires-Python: >=3, <4
Requires-Dist: tensorflow (>=1.14)
Provides-Extra: dev
Requires-Dist: check-manifest ; extra == 'dev'
Provides-Extra: test
Requires-Dist: coverage ; extra == 'test'
Requires-Dist: pytest ; extra == 'test'
Requires-Dist: pytest-pylint ; extra == 'test'
Requires-Dist: pylint ; extra == 'test'
